MANIFEST.in
README.rst
entrypointer.py
requirements.txt
setup.py
test-requirements.txt
test_entrypointer.py
tox.ini
entrypointer.egg-info/PKG-INFO
entrypointer.egg-info/SOURCES.txt
entrypointer.egg-info/dependency_links.txt
entrypointer.egg-info/requires.txt
entrypointer.egg-info/top_level.txt