Metadata-Version: 1.1
Name: entrypointer
Version: 1.0.0
Summary: Object-like Entrypoint Access
Home-page: https://github.com/klmitch/entrypointer
Author: Kevin L. Mitchell
Author-email: klmitch@mit.edu
License: UNKNOWN
Platform: UNKNOWN
Classifier: Development Status :: 5 - Production/Stable
Classifier: Environment :: Plugins
Classifier: Intended Audience :: Developers
Classifier: License :: OSI Approved :: Apache Software License
Classifier: Operating System :: OS Independent
Classifier: Programming Language :: Python :: 2.7
Classifier: Programming Language :: Python :: 3.4
Classifier: Programming Language :: Python :: 3.5
Classifier: Programming Language :: Python :: 3.6
Classifier: Topic :: Software Development :: User Interfaces
